mock_cminor/__init__.py
mock_cminor/__version__.py
mock_cminor/adaptor.py
mock_cminor/analyzers.py
mock_cminor/generator.py
mock_cminor/get_results.py
mock_cminor/utils.py
mock_cminor-0.0.5.dist-info/METADATA
mock_cminor-0.0.5.dist-info/WHEEL
mock_cminor-0.0.5.dist-info/licenses/LICENCE
mock_cminor-0.0.5.dist-info/RECORD
