Metadata-Version: 2.3
Name: mock-cminor
Version: 0.0.5
Summary: Mocking library for Cminor
Project-URL: Homepage, https://github.com/Cathoven-AI/cminor
Project-URL: Issues, https://github.com/Cathoven-AI/cminor/issues
Author-email: "Cathoven A.I" <contact@cathoven.com>
License-File: LICENCE
Classifier: License :: OSI Approved :: MIT License
Classifier: Operating System :: OS Independent
Classifier: Programming Language :: Python :: 3
Requires-Python: >=3.8
